docrag/__init__.py
docrag/cli.py
docrag/config_manager.py
docrag/database_repair.py
docrag/document_processor.py
docrag/errors.py
docrag/mcp_reindex_worker.py
docrag/mcp_server.py
docrag/prompt_templates.py
docrag/py.typed
docrag/security.py
docrag/vector_db.py
docrag_kit-0.2.0.dist-info/licenses/LICENSE
docrag_kit-0.2.0.dist-info/METADATA
docrag_kit-0.2.0.dist-info/WHEEL
docrag_kit-0.2.0.dist-info/entry_points.txt
docrag_kit-0.2.0.dist-info/top_level.txt
docrag_kit-0.2.0.dist-info/RECORD
