Metadata-Version: 2.4
Name: docrag-kit
Version: 0.2.0
Summary: Universal RAG system for project documentation
Author: DocRAG Kit Contributors
License: MIT
Project-URL: Homepage, https://github.com/dexiusprime-oss/docrag-kit
Project-URL: Documentation, https://github.com/dexiusprime-oss/docrag-kit#readme
Project-URL: Repository, https://github.com/dexiusprime-oss/docrag-kit
Project-URL: Issues, https://github.com/dexiusprime-oss/docrag-kit/issues
Keywords: rag,documentation,search,ai,llm,mcp
Classifier: Development Status :: 3 - Alpha
Classifier: Intended Audience :: Developers
Classifier: License :: OSI Approved :: MIT License
Classifier: Programming Language :: Python :: 3
Classifier: Programming Language :: Python :: 3.10
Classifier: Programming Language :: Python :: 3.11
Classifier: Programming Language :: Python :: 3.12
Classifier: Topic :: Software Development :: Documentation
Classifier: Topic :: Text Processing :: Indexing
Requires-Python: >=3.10
License-File: LICENSE
Requires-Dist: click>=8.0.0
Requires-Dist: langchain>=0.1.0
Requires-Dist: langchain-community>=0.0.10
Requires-Dist: langchain-openai>=0.0.5
Requires-Dist: langchain-google-genai>=0.0.5
Requires-Dist: langchain-chroma>=0.1.0
Requires-Dist: chromadb>=0.4.22
Requires-Dist: pyyaml>=6.0
Requires-Dist: python-dotenv>=1.0.0
Requires-Dist: chardet>=5.0.0
Requires-Dist: tiktoken>=0.5.0
Requires-Dist: mcp>=1.0.0
Requires-Dist: psutil>=5.8.0
Provides-Extra: dev
Requires-Dist: pytest>=7.0.0; extra == "dev"
Requires-Dist: pytest-asyncio>=0.21.0; extra == "dev"
Requires-Dist: hypothesis>=6.0.0; extra == "dev"
Requires-Dist: black>=23.0.0; extra == "dev"
Requires-Dist: flake8>=6.0.0; extra == "dev"
Requires-Dist: mypy>=1.0.0; extra == "dev"
Dynamic: license-file
